<?xml version="1.0" encoding="utf-8"?><PSDUI><psdSize><width>1600</width><height>900</height></psdSize><layers><Layer>
<type>Panel</type>
<name>ToggleTemp</name>
<layers><Layer>
<type>Toggle</type>
<name>switch</name>
<images>
<Image>
<imageType>Label</imageType>
<name>Tog</name>
<position><x>-7</x><y>-74</y></position><size><width>40</width><height>22</height></size><arguments><string>28B743</string><string>MicrosoftYaHei</string><string>22</string><string>Tog</string></arguments></Image>
<Image>
<name>b_swtich_1</name>
<arguments><string>#24EA98fe</string></arguments><position><x>0</x><y>-98</y></position><size><width>172</width><height>102</height></size><imageType>Image</imageType>
</Image>
<Image>
<name>m_switch_2</name>
<arguments><string>#0F2CDAfe</string></arguments><position><x>-1</x><y>-97</y></position><size><width>168</width><height>98</height></size><imageType>Image</imageType>
</Image>

</images>
</Layer></layers><images>
<Image>
<name>b_back_3</name>
<arguments><string>#98711Dfe</string></arguments><position><x>-15.5</x><y>-154</y></position><size><width>587</width><height>324</height></size><imageType>Image</imageType>
</Image>

</images>
</Layer></layers></PSDUI>
